hyperevals/__init__.py
hyperevals/__main__.py
hyperevals/cli.py
hyperevals/eval.py
hyperevals/hyperband.py
hyperevals/summary.py
hyperevals-0.1.1.dist-info/licenses/LICENSE
hyperevals-0.1.1.dist-info/METADATA
hyperevals-0.1.1.dist-info/WHEEL
hyperevals-0.1.1.dist-info/entry_points.txt
hyperevals-0.1.1.dist-info/top_level.txt
hyperevals-0.1.1.dist-info/RECORD
